DensityFlow2/DensityFlow.py
DensityFlow2/__init__.py
DensityFlow2/atac/__init__.py
DensityFlow2/atac/utils.py
DensityFlow2/dist/__init__.py
DensityFlow2/dist/negbinomial.py
DensityFlow2/flow/__init__.py
DensityFlow2/flow/flow_stats.py
DensityFlow2/flow/plot_quiver.py
DensityFlow2/perturb/__init__.py
DensityFlow2/perturb/perturb.py
DensityFlow2/utils/__init__.py
DensityFlow2/utils/custom_mlp.py
DensityFlow2/utils/queue.py
DensityFlow2/utils/utils.py
densityflow2-1.3.22.dist-info/licenses/LICENSE
densityflow2-1.3.22.dist-info/METADATA
densityflow2-1.3.22.dist-info/WHEEL
densityflow2-1.3.22.dist-info/entry_points.txt
densityflow2-1.3.22.dist-info/top_level.txt
densityflow2-1.3.22.dist-info/RECORD
